rpi_mail_cam_capture/__init__.py
rpi_mail_cam_capture-0.0.1.dist-info/LICENSE
rpi_mail_cam_capture-0.0.1.dist-info/METADATA
rpi_mail_cam_capture-0.0.1.dist-info/WHEEL
rpi_mail_cam_capture-0.0.1.dist-info/top_level.txt
rpi_mail_cam_capture-0.0.1.dist-info/RECORD
