Metadata-Version: 2.1
Name: rpi-mail-cam-capture
Version: 0.0.1
Summary: You can capture through raspberry pi camera and mail the image
Home-page: https://github.com/ultimus11/email_via_raspberry_pi
Author: sahil panindre
Author-email: sahil11panindre@gmail.com
License: UNKNOWN
Platform: UNKNOWN
Classifier: Programming Language :: Python :: 3
Classifier: License :: OSI Approved :: MIT License
Classifier: Operating System :: OS Independent
